odoo/addons/hr_timesheet_sheet_attendance/README.rst
odoo/addons/hr_timesheet_sheet_attendance/__init__.py
odoo/addons/hr_timesheet_sheet_attendance/__manifest__.py
odoo/addons/hr_timesheet_sheet_attendance/i18n/de.po
odoo/addons/hr_timesheet_sheet_attendance/i18n/hr_timesheet_sheet_attendance.pot
odoo/addons/hr_timesheet_sheet_attendance/models/__init__.py
odoo/addons/hr_timesheet_sheet_attendance/models/hr_attendance.py
odoo/addons/hr_timesheet_sheet_attendance/models/hr_timesheet_sheet.py
odoo/addons/hr_timesheet_sheet_attendance/readme/CONTRIBUTORS.rst
odoo/addons/hr_timesheet_sheet_attendance/readme/DESCRIPTION.rst
odoo/addons/hr_timesheet_sheet_attendance/readme/INSTALL.rst
odoo/addons/hr_timesheet_sheet_attendance/readme/USAGE.rst
odoo/addons/hr_timesheet_sheet_attendance/static/description/icon.png
odoo/addons/hr_timesheet_sheet_attendance/static/description/index.html
odoo/addons/hr_timesheet_sheet_attendance/static/src/css/attendance_matrix_widget.css
odoo/addons/hr_timesheet_sheet_attendance/static/src/js/attendance_matrix_widget.js
odoo/addons/hr_timesheet_sheet_attendance/tests/__init__.py
odoo/addons/hr_timesheet_sheet_attendance/tests/hr_timesheet_sheet_test_cases.py
odoo/addons/hr_timesheet_sheet_attendance/tests/test_attendance_by_day.py
odoo/addons/hr_timesheet_sheet_attendance/tests/test_hr_attendance.py
odoo/addons/hr_timesheet_sheet_attendance/tests/test_hr_timesheet_sheet.py
odoo/addons/hr_timesheet_sheet_attendance/views/assets.xml
odoo/addons/hr_timesheet_sheet_attendance/views/hr_attendance_view.xml
odoo/addons/hr_timesheet_sheet_attendance/views/hr_timesheet_sheet_view.xml
odoo11_addon_hr_timesheet_sheet_attendance-11.0.0.0.2.dist-info/METADATA
odoo11_addon_hr_timesheet_sheet_attendance-11.0.0.0.2.dist-info/WHEEL
odoo11_addon_hr_timesheet_sheet_attendance-11.0.0.0.2.dist-info/top_level.txt
odoo11_addon_hr_timesheet_sheet_attendance-11.0.0.0.2.dist-info/RECORD
